ososedki_dl/__init__.py
ososedki_dl/__main__.py
ososedki_dl/cli.py
ososedki_dl/config.py
ososedki_dl/consts.py
ososedki_dl/crawlers/__init__.py
ososedki_dl/crawlers/base_crawler.py
ososedki_dl/crawlers/ososedki/__init__.py
ososedki_dl/crawlers/ososedki/cosplayasian.py
ososedki_dl/crawlers/ososedki/cosplayboobs.py
ososedki_dl/crawlers/ososedki/cosplayrule34.py
ososedki_dl/crawlers/ososedki/cosplaythots.py
ososedki_dl/crawlers/ososedki/ocosplay.py
ososedki_dl/crawlers/ososedki/ososedki.py
ososedki_dl/crawlers/ososedki/vipthots.py
ososedki_dl/crawlers/ososedki/waifubitches.py
ososedki_dl/crawlers/ososedki_crawler.py
ososedki_dl/crawlers/other/__init__.py
ososedki_dl/crawlers/other/bunkrr_albums.py
ososedki_dl/crawlers/other/cosxuxi_club.py
ososedki_dl/crawlers/other/eromexxx.py
ososedki_dl/crawlers/other/fapello_is.py
ososedki_dl/crawlers/other/husvjjal_blogspot.py
ososedki_dl/crawlers/other/sorrymother.py
ososedki_dl/crawlers/other/wildskirts.py
ososedki_dl/download.py
ososedki_dl/logs.py
ososedki_dl/py.typed
ososedki_dl/scrapper.py
ososedki_dl/utils.py
ososedki_dl-1.1.0.dist-info/entry_points.txt
ososedki_dl-1.1.0.dist-info/LICENSE
ososedki_dl-1.1.0.dist-info/METADATA
ososedki_dl-1.1.0.dist-info/WHEEL
ososedki_dl-1.1.0.dist-info/RECORD
