Metadata-Version: 2.3
Name: ososedki_dl
Version: 1.1.0
Summary: Blazing bulk web scraper for leak sites
License: GPL-3.0-only
Author: Alejandro González Momblán
Author-email: agelrenorenardo@gmail.com
Requires-Python: >=3.9,<4.0
Classifier: License :: OSI Approved :: GNU General Public License v3 (GPLv3)
Classifier: Programming Language :: Python :: 3
Classifier: Programming Language :: Python :: 3.9
Classifier: Programming Language :: Python :: 3.10
Classifier: Programming Language :: Python :: 3.11
Classifier: Programming Language :: Python :: 3.12
Classifier: Programming Language :: Python :: 3.13
Requires-Dist: aiofiles (>=24.1.0,<25.0.0)
Requires-Dist: aiohttp (>=3.8,<4.0.0)
Requires-Dist: aiohttp-client-cache (>=0.13.0,<0.14.0)
Requires-Dist: beautifulsoup4 (>=4.12.2,<5.0.0)
Requires-Dist: core-helpers (>=1.3.1,<2.0.0)
Requires-Dist: fake-useragent (>=1.5.1,<3.0.0)
Requires-Dist: requests (>=2.31.0,<3.0.0)
Requires-Dist: rich (>=13.5.3)
Requires-Dist: tldextract (>=5.1.2,<6.0.0)
Requires-Dist: validators (>=0)
Project-URL: Repository, https://github.com/YisusChrist/ososedki_dl
